{"timestamp": 1513080511761, "created_at": 1513083928271, "value": 1.0, "context": {"eventId": 13, "timeSynced": false}}
{"timestamp": 1513080510361, "created_at": 1513083926775, "value": 0.0, "context": {"eventId": 12, "timeSynced": false}}
{"timestamp": 1513079559561, "created_at": 1513083402659, "value": 1.0, "context": {"eventId": 11, "timeSynced": false}}
{"timestamp": 1513079228755, "created_at": 1513083402573, "value": 0.0, "context": {"eventId": 10, "timeSynced": false}}
{"timestamp": 1513078597067, "created_at": 1513083627731, "value": 1.0, "context": {"eventId": 9, "timeSynced": false}}
{"timestamp": 1513078176059, "created_at": 1513083627551, "value": 0.0, "context": {"eventId": 8, "timeSynced": false}}
{"timestamp": 1513078161759, "created_at": 1513083627505, "value": 1.0, "context": {"eventId": 7, "timeSynced": false}}
{"timestamp": 1513078042361, "created_at": 1513083621688, "value": 0.0, "context": {"eventId": 6, "timeSynced": false}}
{"timestamp": 1513077517362, "created_at": 1513083621394, "value": 1.0, "context": {"eventId": 5, "timeSynced": false}}
{"timestamp": 1513077317362, "created_at": 1513083621112, "value": 0.0, "context": {"eventId": 4, "timeSynced": false}}
{"timestamp": 1513077057965, "created_at": 1513083645909, "value": 1.0, "context": {"eventId": 3, "timeSynced": false}}
{"timestamp": 1513077011166, "created_at": 1513083645857, "value": 0.0, "context": {"eventId": 2, "timeSynced": false}}
{"timestamp": 1513075568859, "created_at": 1513083384115, "value": 1.0, "context": {"eventId": 1, "timeSynced": false}}
{"timestamp": 1513075483961, "created_at": 1513083383196, "value": 0.0, "context": {"eventId": 0, "timeSynced": false}}
{"timestamp": 1513050491295, "created_at": 1513083396266, "value": 0.0, "context": {"eventId": 4, "timeSynced": false}}
{"timestamp": 1513050489195, "created_at": 1513083396025, "value": 1.0, "context": {"eventId": 3, "timeSynced": false}}
{"timestamp": 1513050486195, "created_at": 1513083396045, "value": 0.0, "context": {"eventId": 2, "timeSynced": false}}
{"timestamp": 1513050315395, "created_at": 1513083396218, "value": 1.0, "context": {"eventId": 1, "timeSynced": false}}
{"timestamp": 1513049859772, "created_at": 1513053729339, "value": 0.0, "context": {"eventId": 0, "timeSynced": false}}
{"timestamp": 1513048659093, "created_at": 1513049325569, "value": 1.0, "context": {"eventId": 0, "timeSynced": true}}
{"timestamp": 1513003268303, "created_at": 1513047863725, "value": 1.0, "context": {"eventId": 17, "timeSynced": false}}
{"timestamp": 1513002803003, "created_at": 1513047863045, "value": 0.0, "context": {"eventId": 16, "timeSynced": false}}
{"timestamp": 1513002643804, "created_at": 1513047857010, "value": 1.0, "context": {"eventId": 15, "timeSynced": false}}
{"timestamp": 1513001806405, "created_at": 1513047856286, "value": 0.0, "context": {"eventId": 14, "timeSynced": false}}
{"timestamp": 1513001722805, "created_at": 1513047851790, "value": 1.0, "context": {"eventId": 13, "timeSynced": false}}
{"timestamp": 1513001415705, "created_at": 1513047850849, "value": 0.0, "context": {"eventId": 12, "timeSynced": false}}
{"timestamp": 1513001163301, "created_at": 1513047849967, "value": 1.0, "context": {"eventId": 11, "timeSynced": false}}
{"timestamp": 1513000744341, "created_at": 1513047846364, "value": 0.0, "context": {"eventId": 10, "timeSynced": false}}
{"timestamp": 1513000650141, "created_at": 1513047845523, "value": 1.0, "context": {"eventId": 9, "timeSynced": false}}
{"timestamp": 1513000322038, "created_at": 1513047844979, "value": 0.0, "context": {"eventId": 8, "timeSynced": false}}
{"timestamp": 1513000305838, "created_at": 1513047844474, "value": 1.0, "context": {"eventId": 7, "timeSynced": false}}
{"timestamp": 1513000255045, "created_at": 1513047843671, "value": 0.0, "context": {"eventId": 6, "timeSynced": false}}
{"timestamp": 1513000251845, "created_at": 1513047842672, "value": 1.0, "context": {"eventId": 5, "timeSynced": false}}
{"timestamp": 1512999927211, "created_at": 1513047838602, "value": 0.0, "context": {"eventId": 4, "timeSynced": false}}
{"timestamp": 1512999561715, "created_at": 1513047837568, "value": 1.0, "context": {"eventId": 3, "timeSynced": false}}
{"timestamp": 1512999169414, "created_at": 1513047836617, "value": 0.0, "context": {"eventId": 2, "timeSynced": false}}
{"timestamp": 1512998581565, "created_at": 1513047832962, "value": 1.0, "context": {"eventId": 1, "timeSynced": false}}
{"timestamp": 1512998280752, "created_at": 1513047832918, "value": 0.0, "context": {"eventId": 0, "timeSynced": false}}
{"timestamp": 1512998205344, "created_at": 1513047881691, "value": 0.0, "context": {"eventId": 11, "timeSynced": true}}
{"timestamp": 1512997747043, "created_at": 1513047880875, "value": 1.0, "context": {"eventId": 10, "timeSynced": true}}
{"timestamp": 1512997494938, "created_at": 1513047880319, "value": 0.0, "context": {"eventId": 9, "timeSynced": true}}
{"timestamp": 1512996826547, "created_at": 1513047874540, "value": 1.0, "context": {"eventId": 8, "timeSynced": true}}
{"timestamp": 1512996765318, "created_at": 1513047873678, "value": 0.0, "context": {"eventId": 7, "timeSynced": true}}
{"timestamp": 1512993864404, "created_at": 1513047894867, "value": 1.0, "context": {"eventId": 6, "timeSynced": true}}
{"timestamp": 1512993655731, "created_at": 1512993836516, "value": 0.0, "context": {"eventId": 5, "timeSynced": true}}
{"timestamp": 1512993383513, "created_at": 1512993512101, "value": 1.0, "context": {"eventId": 4, "timeSynced": true}}
{"timestamp": 1512993254913, "created_at": 1512993512083, "value": 0.0, "context": {"eventId": 3, "timeSynced": true}}
{"timestamp": 1512993253613, "created_at": 1512993511973, "value": 1.0, "context": {"eventId": 2, "timeSynced": true}}
{"timestamp": 1512993218214, "created_at": 1512993511830, "value": 0.0, "context": {"eventId": 1, "timeSynced": true}}
{"timestamp": 1512993122261, "created_at": 1512993210604, "value": 1.0, "context": {"eventId": 0, "timeSynced": true}}
{"timestamp": 1512975758873, "created_at": 1512993028718, "value": 1.0, "context": {"eventId": 1, "timeSynced": true}}
{"timestamp": 1512975022312, "created_at": 1512992987476, "value": 0.0, "context": {"eventId": 0, "timeSynced": true}}
{"timestamp": 1512892269891, "created_at": 1512974513467, "value": 1.0, "context": {"eventId": 39, "timeSynced": true}}
{"timestamp": 1512892269792, "created_at": 1512974513458, "value": 0.0, "context": {"eventId": 38, "timeSynced": true}}
{"timestamp": 1512892261491, "created_at": 1512974513383, "value": 1.0, "context": {"eventId": 37, "timeSynced": true}}
{"timestamp": 1512892261392, "created_at": 1512974513343, "value": 0.0, "context": {"eventId": 36, "timeSynced": true}}
{"timestamp": 1512892249891, "created_at": 1512974513234, "value": 1.0, "context": {"eventId": 35, "timeSynced": true}}
{"timestamp": 1512892249793, "created_at": 1512974513199, "value": 0.0, "context": {"eventId": 34, "timeSynced": true}}
{"timestamp": 1512892239493, "created_at": 1512974513118, "value": 1.0, "context": {"eventId": 33, "timeSynced": true}}
{"timestamp": 1512892239391, "created_at": 1512974512929, "value": 0.0, "context": {"eventId": 32, "timeSynced": true}}
{"timestamp": 1512892239190, "created_at": 1512974512690, "value": 1.0, "context": {"eventId": 31, "timeSynced": true}}
{"timestamp": 1512892239092, "created_at": 1512974512560, "value": 0.0, "context": {"eventId": 30, "timeSynced": true}}
{"timestamp": 1512892230390, "created_at": 1512974512528, "value": 1.0, "context": {"eventId": 29, "timeSynced": true}}
{"timestamp": 1512892230291, "created_at": 1512974512440, "value": 0.0, "context": {"eventId": 28, "timeSynced": true}}
{"timestamp": 1512892217490, "created_at": 1512974512402, "value": 1.0, "context": {"eventId": 27, "timeSynced": true}}
{"timestamp": 1512892217391, "created_at": 1512974512338, "value": 0.0, "context": {"eventId": 26, "timeSynced": true}}
{"timestamp": 1512892208290, "created_at": 1512974512249, "value": 1.0, "context": {"eventId": 25, "timeSynced": true}}
{"timestamp": 1512892208191, "created_at": 1512974512174, "value": 0.0, "context": {"eventId": 24, "timeSynced": true}}
{"timestamp": 1512892187590, "created_at": 1512974512169, "value": 1.0, "context": {"eventId": 23, "timeSynced": true}}
{"timestamp": 1512892187491, "created_at": 1512974512117, "value": 0.0, "context": {"eventId": 22, "timeSynced": true}}
{"timestamp": 1512892173990, "created_at": 1512974512112, "value": 1.0, "context": {"eventId": 21, "timeSynced": true}}
{"timestamp": 1512892173892, "created_at": 1512974512046, "value": 0.0, "context": {"eventId": 20, "timeSynced": true}}
{"timestamp": 1512892158383, "created_at": 1512974499241, "value": 1.0, "context": {"eventId": 19, "timeSynced": true}}
{"timestamp": 1512892158284, "created_at": 1512974499144, "value": 0.0, "context": {"eventId": 18, "timeSynced": true}}
{"timestamp": 1512892147283, "created_at": 1512974499097, "value": 1.0, "context": {"eventId": 17, "timeSynced": true}}
{"timestamp": 1512892147184, "created_at": 1512974498859, "value": 0.0, "context": {"eventId": 16, "timeSynced": true}}
{"timestamp": 1512892135682, "created_at": 1512974498760, "value": 1.0, "context": {"eventId": 15, "timeSynced": true}}
{"timestamp": 1512892135584, "created_at": 1512974498723, "value": 0.0, "context": {"eventId": 14, "timeSynced": true}}
{"timestamp": 1512892131682, "created_at": 1512974498705, "value": 1.0, "context": {"eventId": 13, "timeSynced": true}}
{"timestamp": 1512892131583, "created_at": 1512974498671, "value": 0.0, "context": {"eventId": 12, "timeSynced": true}}
{"timestamp": 1512892125782, "created_at": 1512974498634, "value": 1.0, "context": {"eventId": 11, "timeSynced": true}}
{"timestamp": 1512892125682, "created_at": 1512974498598, "value": 0.0, "context": {"eventId": 10, "timeSynced": true}}
{"timestamp": 1512892033093, "created_at": 1512974498571, "value": 1.0, "context": {"eventId": 9, "timeSynced": true}}
{"timestamp": 1512892032994, "created_at": 1512974498531, "value": 0.0, "context": {"eventId": 8, "timeSynced": true}}
{"timestamp": 1512891772133, "created_at": 1512974498439, "value": 1.0, "context": {"eventId": 7, "timeSynced": false}}
{"timestamp": 1512891772035, "created_at": 1512974498419, "value": 0.0, "context": {"eventId": 6, "timeSynced": false}}
{"timestamp": 1512891749235, "created_at": 1512974498389, "value": 1.0, "context": {"eventId": 5, "timeSynced": false}}
{"timestamp": 1512891745634, "created_at": 1512974498353, "value": 0.0, "context": {"eventId": 4, "timeSynced": false}}
{"timestamp": 1512891743835, "created_at": 1512974498327, "value": 1.0, "context": {"eventId": 3, "timeSynced": false}}
{"timestamp": 1512891742135, "created_at": 1512974498273, "value": 0.0, "context": {"eventId": 2, "timeSynced": false}}
{"timestamp": 1512891738934, "created_at": 1512974498161, "value": 1.0, "context": {"eventId": 1, "timeSynced": false}}
{"timestamp": 1512891738836, "created_at": 1512974498065, "value": 0.0, "context": {"eventId": 0, "timeSynced": false}}
{"timestamp": 1512890567975, "created_at": 1512892045862, "value": 1.0, "context": {"eventId": 2, "timeSynced": true}}
{"timestamp": 1512890315885, "created_at": 1512892045821, "value": 0.0, "context": {"eventId": 1, "timeSynced": true}}
{"timestamp": 1512890294291, "created_at": 1512892045791, "value": 1.0, "context": {"eventId": 0, "timeSynced": true}}
